webint_tracker/__init__.py
webint_tracker/templates/__init__.py
webint_tracker/templates/index.html
webint_tracker/templates/physical.html
webint_tracker/templates/trip.html
webint_tracker/templates/web.html
webint_tracker-0.0.3.dist-info/METADATA
webint_tracker-0.0.3.dist-info/entry_points.txt
webint_tracker-0.0.3.dist-info/WHEEL
webint_tracker-0.0.3.dist-info/RECORD
